{"_id": "cfa26950d2dbbea3863dfc532a8001e62007db3292694835b3f7d8a39fac5f50", "version": "v11.02.hf6", "date": "2024-03-25T15:20:00.000Z", "queueType": "Normal", "endingWave": 9, "gameLength": 844, "gameElo": 2101, "playerCount": 4, "humanCount": 4, "spellChoices": ["dark_ritual_powerup_id", "magician_powerup_id", "sorcerer_spell_damage_powerup_id"], "leftKingPercentHp": [1, 1, 1, 1, 1, 0.975, 0.975, 0.765, 0.7633504], "rightKingPercentHp": [1, 1, 1, 0.76, 0.76, 0.465, 0.47, 0.48, 0], "kingSpell": "lightning_hammer_activator_ability_id", "incomenchill": false, "votedmode": null, "playersData": [{"playerId": "5859032C0513BC16", "playerName": "Botzi", "playerSlot": 1, "legion": "Cartel", "workers": 12, "value": 1180, "cross": false, "gameResult": "won", "classicElo": 4536, "overallElo": 2211, "eloChange": 14, "fighters": "Gatling Gun,Pirate Skeleton,Veteran,Mudman,Veteran,Azeria", "eco": false, "mercenaries": "Snail,Brute,Snail,Cannoneer,Robo,Ogre,Safety Mole,Robo", "stayedUntilEnd": true, "chosenSpell": "none", "chosenSpellLocation": "-1|-1", "partySize": 1, "firstWaveFighters": "Priestess Of The Abyss", "rolls": "peewee_unit_id, pirate_skeleton_unit_id, mudman_unit_id, priestess_of_the_abyss_unit_id, gatling_gun_unit_id, shadow_dancer_unit_id", "legionSpecificElo": 2342, "partyMembers": ["Botzi"], "partyMembersIds": ["5859032C0513BC16"], "mvpScore": 2068, "netWorthPerWave": [437, 554, 686, 869, 1066, 1262, 1453, 1791, 1969], "valuePerWave": [190, 190, 215, 380, 380, 560, 640, 830, 1180], "workersPerWave": [4, 6, 6, 8, 10, 12, 12, 12, 12], "incomePerWave": [15, 21, 36, 42, 72, 82, 82, 162, 162], "mercenariesSentPerWave": [[], ["Snail"], [], ["Brute", "Snail"], [], ["Cannoneer", "Robo"], [], [], ["Ogre", "Safety Mole", "Robo"]], "mercenariesReceivedPerWave": [[], [], ["Snail"], ["Dragon Turtle", "Snail"], ["Dragon Turtle"], ["Fiend"], ["Brute", "Snail"], ["Cannoneer", "Lizard"], ["Dino", "Robo"]], "leaksPerWave": [[], [], [], [], [], ["Rocko", "Rocko", "Rocko", "Rocko", "Rocko", "Rocko"], ["Blob", "Blob", "Blob", "Blob", "Sludge", "Sludge", "Brute"], [], []], "buildPerWave": [["priestess_of_the_abyss_unit_id:0.5|11.5:0"], ["priestess_of_the_abyss_unit_id:0.5|11.5:0"], ["priestess_of_the_abyss_unit_id:0.5|11.5:0", "peewee_unit_id:8.5|9:0"], ["priestess_of_the_abyss_unit_id:0.5|11.5:0", "peewee_unit_id:8.5|9:0", "mudman_unit_id:1.5|4.5:0", "peewee_unit_id:6.5|8.5:0"], ["priestess_of_the_abyss_unit_id:0.5|11.5:0", "peewee_unit_id:8.5|9:0", "mudman_unit_id:1.5|4.5:0", "peewee_unit_id:6.5|8.5:0"], ["priestess_of_the_abyss_unit_id:0.5|11.5:0", "veteran_unit_id:8.5|9:0", "mudman_unit_id:1.5|4.5:0", "veteran_unit_id:6.5|8.5:0"], ["priestess_of_the_abyss_unit_id:0.5|11.5:0", "veteran_unit_id:8.5|9:0", "mudman_unit_id:1.5|4.5:0", "veteran_unit_id:6.5|8.5:0", "pirate_skeleton_unit_id:0.5|5:0"], ["priestess_of_the_abyss_unit_id:0.5|11.5:0", "veteran_unit_id:8.5|9:0", "mudman_unit_id:1.5|4.5:1", "veteran_unit_id:6.5|8.5:0", "pirate_skeleton_unit_id:0.5|5:0", "gatling_gun_unit_id:0.5|10.5:0"], ["azeria_unit_id:0.5|11.5:0", "veteran_unit_id:8.5|9:0", "mudman_unit_id:1.5|4.5:-1", "veteran_unit_id:6.5|8.5:0", "pirate_skeleton_unit_id:0.5|5:0", "gatling_gun_unit_id:0.5|10.5:0"]], "leakValue": 100, "leaksCaughtValue": 22, "leftAtSeconds": -1, "kingUpgradesPerWave": [["Upgrade King Attack"], [], [], [], [], [], [], [], []], "opponentKingUpgradesPerWave": [["Upgrade King Spell"], ["Upgrade King Spell"], [], [], [], [], [], [], []], "megamind": false, "chosenChampionLocation": "-1|-1"}, {"playerId": "3FEEDFE12ACDCCCD", "playerName": "shizo", "playerSlot": 2, "legion": "Greed", "workers": 17, "value": 975, "cross": false, "gameResult": "won", "classicElo": 1794, "overallElo": 2038, "eloChange": 14, "fighters": "Gargoyle,Daphne,Head Chef,Daphne,Green Devil", "eco": false, "mercenaries": "Brute,Snail,Robo,Robo,Robo,Dino,Pack Leader,Safety Mole,Robo,Robo", "stayedUntilEnd": true, "chosenSpell": "none", "chosenSpellLocation": "-1|-1", "partySize": 1, "firstWaveFighters": "Green Devil", "rolls": "looter_unit_id, gargoyle_unit_id, ranger_unit_id, butcher_unit_id, priestess_of_the_abyss_unit_id, great_boar_unit_id", "legionSpecificElo": 1686, "partyMembers": ["shizo"], "partyMembersIds": ["3FEEDFE12ACDCCCD"], "mvpScore": 2825, "netWorthPerWave": [433, 558, 692, 858, 1063, 1341, 1561, 1829, 1973], "valuePerWave": [160, 215, 215, 340, 490, 545, 670, 710, 975], "workersPerWave": [4, 6, 6, 7, 9, 12, 15, 17, 17], "incomePerWave": [11, 17, 32, 38, 58, 92, 92, 162, 182], "mercenariesSentPerWave": [[], [], [], ["Brute", "Snail"], [], ["Robo", "Robo", "Robo"], ["Dino"], [], ["Pack Leader", "Safety Mole", "Robo", "Robo"]], "mercenariesReceivedPerWave": [[], ["Snail", "Snail"], ["Lizard"], ["Snail"], ["Lizard", "Lizard"], ["Lizard"], [], ["Safety Mole", "Fiend", "Snail"], ["Hermit"]], "leaksPerWave": [[], [], [], [], [], [], [], ["Kobra", "Kobra", "Kobra", "Kobra", "Kobra", "Kobra", "Kobra", "Kobra", "Kobra", "Kobra"], []], "buildPerWave": [["green_devil_unit_id:8.5|6.5:0"], ["green_devil_unit_id:8.5|6.5:0", "ranger_unit_id:0.5|6.5:0"], ["green_devil_unit_id:8.5|6.5:0", "ranger_unit_id:0.5|6.5:0"], ["green_devil_unit_id:8.5|6.5:0", "daphne_unit_id:0.5|6.5:0"], ["green_devil_unit_id:8.5|6.5:0", "daphne_unit_id:0.5|6.5:0", "butcher_unit_id:7.5|6:0"], ["green_devil_unit_id:8.5|6.5:0", "daphne_unit_id:0.5|6.5:0", "butcher_unit_id:7.5|6:0", "ranger_unit_id:0.5|5.5:0"], ["green_devil_unit_id:8.5|6.5:0", "daphne_unit_id:0.5|6.5:0", "butcher_unit_id:7.5|6:0", "daphne_unit_id:0.5|5.5:0"], ["green_devil_unit_id:8.5|6.5:0", "daphne_unit_id:0.5|6.5:0", "butcher_unit_id:7.5|6:0", "daphne_unit_id:0.5|5.5:0", "gargoyle_unit_id:6.5|5.5:0"], ["green_devil_unit_id:8.5|6.5:0", "daphne_unit_id:0.5|6.5:0", "head_chef_unit_id:7.5|6:0", "daphne_unit_id:0.5|5.5:0", "gargoyle_unit_id:6.5|5.5:0"]], "leakValue": 80, "leaksCaughtValue": 119, "leftAtSeconds": -1, "kingUpgradesPerWave": [["Upgrade King Attack"], ["Upgrade King Spell"], [], [], [], [], [], [], []], "opponentKingUpgradesPerWave": [[], [], ["Upgrade King Attack"], [], [], ["Upgrade King Regen"], [], [], ["Upgrade King Attack"]], "megamind": false, "chosenChampionLocation": "-1|-1"}, {"playerId": "1F0E16EA046602D8", "playerName": "DarknessBrolyReborn", "playerSlot": 5, "legion": "Fiesta", "workers": 10, "value": 1310, "cross": false, "gameResult": "lost", "classicElo": 1613, "overallElo": 2078, "eloChange": -14, "fighters": "Shadow Dancer,Shadow Dancer,Seadragon,Sacred Steed,Chained Fist,Seadragon,Sacred Steed,Oathbreaker,Seadragon,Chained Fist,Oathbreaker,Oathbreaker", "eco": false, "mercenaries": "Snail,Snail,Lizard,Snail,Lizard,Lizard,Lizard,Safety Mole,Fiend,Snail,Hermit", "stayedUntilEnd": true, "chosenSpell": "none", "chosenSpellLocation": "-1|-1", "partySize": 1, "firstWaveFighters": "Oathbreaker", "rolls": "chained_fist_unit_id, sacred_steed_unit_id, seadragon_unit_id, grarl_unit_id, aps_unit_id, shadow_dancer_unit_id", "legionSpecificElo": 800, "partyMembers": ["DarknessBrolyReborn"], "partyMembersIds": ["1F0E16EA046602D8"], "mvpScore": 1261, "netWorthPerWave": [428, 521, 647, 806, 991, 1224, 1481, 1819, 1953], "valuePerWave": [95, 115, 210, 345, 345, 540, 715, 965, 1310], "workersPerWave": [5, 6, 6, 8, 9, 10, 10, 10, 10], "incomePerWave": [6, 24, 36, 48, 72, 78, 126, 152, 158], "mercenariesSentPerWave": [[], ["Snail", "Snail"], ["Lizard"], ["Snail"], ["Lizard", "Lizard"], ["Lizard"], [], ["Safety Mole", "Fiend", "Snail"], ["Hermit"]], "mercenariesReceivedPerWave": [[], ["Snail"], [], ["Brute", "Snail"], [], ["Cannoneer", "Robo"], [], [], ["Ogre", "Safety Mole", "Robo"]], "leaksPerWave": [[], ["Wale", "Wale", "Wale", "Wale", "Wale", "Wale", "Wale", "Wale", "Wale", "Wale", "Wale", "Wale"], [], ["Flying Chicken", "Flying Chicken", "Flying Chicken", "Flying Chicken", "Flying Chicken", "Brute"], [], ["Rocko", "Rocko", "Robo", "Cannoneer"], [], [], []], "buildPerWave": [["oathbreaker_unit_id:8.5|10.5:0"], ["oathbreaker_unit_id:8.5|10.5:0", "chained_fist_unit_id:0.5|10.5:0"], ["oathbreaker_unit_id:8.5|10.5:0", "oathbreaker_unit_id:0.5|10.5:0", "chained_fist_unit_id:1.5|10:0"], ["oathbreaker_unit_id:8.5|10.5:0", "oathbreaker_unit_id:0.5|10.5:0", "chained_fist_unit_id:1.5|10:0", "seadragon_unit_id:2.5|7:0", "chained_fist_unit_id:7.5|10:0", "chained_fist_unit_id:6.5|9.5:0"], ["oathbreaker_unit_id:8.5|10.5:0", "oathbreaker_unit_id:0.5|10.5:0", "chained_fist_unit_id:1.5|10:0", "seadragon_unit_id:2.5|7:0", "chained_fist_unit_id:7.5|10:0", "chained_fist_unit_id:6.5|9.5:0"], ["oathbreaker_unit_id:8.5|10.5:0", "oathbreaker_unit_id:0.5|10.5:0", "chained_fist_unit_id:1.5|10:0", "seadragon_unit_id:2.5|7:0", "chained_fist_unit_id:7.5|10:0", "chained_fist_unit_id:6.5|9.5:0", "sacred_steed_unit_id:2|8:0", "seadragon_unit_id:1.5|7:0", "chained_fist_unit_id:2.5|9.5:0"], ["oathbreaker_unit_id:8.5|10.5:0", "oathbreaker_unit_id:0.5|10.5:0", "chained_fist_unit_id:1.5|10:0", "seadragon_unit_id:2.5|7:0", "chained_fist_unit_id:7.5|10:0", "chained_fist_unit_id:6.5|9.5:0", "sacred_steed_unit_id:2|8:0", "seadragon_unit_id:1.5|7:0", "chained_fist_unit_id:2.5|9.5:0", "sacred_steed_unit_id:3|8:0", "seadragon_unit_id:3.5|7:0"], ["oathbreaker_unit_id:8.5|10.5:0", "oathbreaker_unit_id:0.5|10.5:0", "chained_fist_unit_id:1.5|10:0", "seadragon_unit_id:2.5|7:0", "chained_fist_unit_id:7.5|10:0", "sacred_steed_unit_id:2|8:0", "seadragon_unit_id:1.5|7:0", "chained_fist_unit_id:2.5|9.5:0", "sacred_steed_unit_id:3|8:0", "seadragon_unit_id:3.5|7:0", "shadow_dancer_unit_id:8|6.5:0"], ["oathbreaker_unit_id:8.5|10.5:0", "oathbreaker_unit_id:0.5|10.5:0", "chained_fist_unit_id:1.5|10:0", "seadragon_unit_id:2.5|7:0", "oathbreaker_unit_id:7.5|10:0", "sacred_steed_unit_id:2|8:0", "seadragon_unit_id:1.5|7:0", "chained_fist_unit_id:2.5|9.5:0", "sacred_steed_unit_id:3|8:0", "seadragon_unit_id:3.5|7:0", "shadow_dancer_unit_id:8|6.5:0", "shadow_dancer_unit_id:7.5|5.5:0"]], "leakValue": 108, "leaksCaughtValue": 45, "leftAtSeconds": -1, "kingUpgradesPerWave": [[], [], ["Upgrade King Attack"], [], [], ["Upgrade King Regen"], [], [], ["Upgrade King Attack"]], "opponentKingUpgradesPerWave": [["Upgrade King Attack"], [], [], [], [], [], [], [], []], "megamind": false, "chosenChampionLocation": "-1|-1"}, {"playerId": "4327A38B1DE7A902", "playerName": "jbombard", "playerSlot": 6, "legion": "Yolo", "workers": 12, "value": 1240, "cross": false, "gameResult": "lost", "classicElo": 1414, "overallElo": 2078, "eloChange": -14, "fighters": "Iron Maiden,Priestess Of The Abyss,Sea Serpent,Sea Serpent,Azeria", "eco": false, "mercenaries": "Snail,Dragon Turtle,Snail,Dragon Turtle,Fiend,Brute,Snail,Cannoneer,Lizard,Dino,Robo", "stayedUntilEnd": true, "chosenSpell": "none", "chosenSpellLocation": "-1|-1", "partySize": 1, "firstWaveFighters": "Priestess Of The Abyss", "rolls": "tempest_unit_id, sea_serpent_unit_id, cursed_casket_unit_id, aps_unit_id, priestess_of_the_abyss_unit_id, gatling_gun_unit_id", "legionSpecificElo": 2193, "partyMembers": ["jbombard"], "partyMembersIds": ["4327A38B1DE7A902"], "mvpScore": 1483, "netWorthPerWave": [435, 556, 683, 833, 989, 1240, 1526, 1850, 1942], "valuePerWave": [190, 190, 190, 370, 370, 560, 790, 890, 1240], "workersPerWave": [4, 6, 6, 7, 8, 9, 12, 12, 12], "incomePerWave": [13, 25, 37, 55, 73, 94, 124, 160, 170], "mercenariesSentPerWave": [[], [], ["Snail"], ["Dragon Turtle", "Snail"], ["Dragon Turtle"], ["Fiend"], ["Brute", "Snail"], ["Cannoneer", "Lizard"], ["Dino", "Robo"]], "mercenariesReceivedPerWave": [[], [], [], ["Brute", "Snail"], [], ["Robo", "Robo", "Robo"], ["Dino"], [], ["Pack Leader", "Safety Mole", "Robo", "Robo"]], "leaksPerWave": [[], [], [], ["Flying Chicken", "Flying Chicken", "Flying Chicken", "Flying Chicken", "Brute"], ["Scorpion", "Scorpion", "Scorpion", "Scorpion", "Scorpion"], ["Rocko", "Rocko", "Rocko", "Robo"], [], [], ["Carapace", "Carapace", "Carapace", "Carapace", "Carapace", "Carapace", "Safety Mole", "Pack Leader"]], "buildPerWave": [["priestess_of_the_abyss_unit_id:0.5|6:0"], ["priestess_of_the_abyss_unit_id:0.5|6:0"], ["priestess_of_the_abyss_unit_id:0.5|6:0"], ["priestess_of_the_abyss_unit_id:0.5|6:0", "sea_serpent_unit_id:2.5|13.5:0", "sea_serpent_unit_id:1.5|13.5:0"], ["priestess_of_the_abyss_unit_id:0.5|6:0", "sea_serpent_unit_id:2.5|13.5:0", "sea_serpent_unit_id:1.5|13.5:0"], ["priestess_of_the_abyss_unit_id:0.5|6:0", "sea_serpent_unit_id:2.5|13.5:0", "sea_serpent_unit_id:1.5|13.5:0", "priestess_of_the_abyss_unit_id:8.5|6:0"], ["priestess_of_the_abyss_unit_id:0.5|6:0", "sea_serpent_unit_id:2.5|13.5:0", "sea_serpent_unit_id:1.5|13.5:0", "priestess_of_the_abyss_unit_id:8.5|6:0", "cage_of_pain_unit_id:0.5|2:0"], ["priestess_of_the_abyss_unit_id:0.5|6:0", "sea_serpent_unit_id:2.5|13.5:0", "sea_serpent_unit_id:1.5|13.5:0", "priestess_of_the_abyss_unit_id:8.5|6:0", "iron_maiden_unit_id:0.5|2:0"], ["azeria_unit_id:0.5|6:0", "sea_serpent_unit_id:2.5|13.5:0", "sea_serpent_unit_id:1.5|13.5:0", "priestess_of_the_abyss_unit_id:8.5|6:0", "iron_maiden_unit_id:0.5|2:0"]], "leakValue": 84, "leaksCaughtValue": 84, "leftAtSeconds": -1, "kingUpgradesPerWave": [["Upgrade King Spell"], ["Upgrade King Spell"], [], [], [], [], [], [], []], "opponentKingUpgradesPerWave": [["Upgrade King Attack"], ["Upgrade King Spell"], [], [], [], [], [], [], []], "megamind": false, "chosenChampionLocation": "-1|-1"}]}