{"_id": "e86eae8c2eef9dffd1e04450fa359c63c1a5266e01ac0bf453e45e82cfb83f3c", "version": "v11.02.hf6", "date": "2024-03-27T06:37:00.000Z", "queueType": "Normal", "endingWave": 16, "gameLength": 1473, "gameElo": 2086, "playerCount": 4, "humanCount": 4, "spellChoices": ["pawn_shop_powerup_id", "robo_squad_powerup_id", "press_the_attack_powerup_id"], "leftKingPercentHp": [1, 1, 1, 1, 1, 1, 1, 1, 0.935, 0.935, 0.935, 0.935, 0.935, 0.565, 0.565, 0.5663552], "rightKingPercentHp": [1, 1, 1, 0.79, 0.71, 0.64, 0.65, 0.67, 0.7, 0.725, 0.2, 0.245, 0.3, 0.385, 0.45, 0], "kingSpell": "lightning_hammer_activator_ability_id", "incomenchill": false, "votedmode": null, "playersData": [{"playerId": "906C137BD0F81FD9", "playerName": "Stars", "playerSlot": 1, "legion": "Champion", "workers": 44.1522, "value": 3750, "cross": false, "gameResult": "won", "classicElo": 2002, "overallElo": 1987, "eloChange": 12, "fighters": "Golden Buckler,Golden Buckler,Golden Buckler,Disciple,Priestess Of The Abyss,Gargoyle,Gargoyle,Gargoyle,Azeria,Green Devil,Starcaller,Royal Guard,Gargoyle,Green Devil,Green Devil,Chained Fist,Elite Archer,Chained Fist,Gargoyle,Royal Guard,Royal Guard,Royal Guard,Azeria", "eco": false, "mercenaries": "Snail,Snail,Robo,Robo,Snail,Robo,Snail,Robo,Robo,Robo,Brute,Dragon Turtle,Snail,Fiend,Witch,Witch,Witch,Dino,Centaur,Centaur,Centaur,Centaur,Pack Leader,Brute,Brute,Brute,Brute", "stayedUntilEnd": true, "chosenSpell": "Press the Attack", "chosenSpellLocation": "-1|-1", "partySize": 2, "firstWaveFighters": "Priestess Of The Abyss", "rolls": "chained_fist_unit_id, gargoyle_unit_id, golden_buckler_unit_id, elite_archer_unit_id, priestess_of_the_abyss_unit_id, disciple_unit_id", "legionSpecificElo": 2206, "partyMembers": ["Stars", "Flittermouse"], "partyMembersIds": ["906C137BD0F81FD9", "9DAE2CCE11E04B12"], "mvpScore": 5778, "netWorthPerWave": [445, 559, 693, 882, 1099, 1367, 1646, 1937, 2245, 2711, 3409, 3892, 4387, 4833, 5719, 6089], "valuePerWave": [190, 190, 190, 290, 380, 535, 700, 840, 1025, 1240, 1510, 1900, 2290, 2785, 3055, 3750], "workersPerWave": [4, 7, 8, 10, 11, 13, 15, 18, 20, 23, 28.542137, 33.30431, 33.30431, 36.26431, 44.1522, 44.1522], "incomePerWave": [12, 18, 38, 54, 80, 111, 141, 141, 141, 265, 315, 315, 315, 315, 650, 680], "mercenariesSentPerWave": [[], ["Snail", "Snail"], [], ["Robo", "Robo", "Snail"], ["Robo", "Snail"], ["Robo", "Robo", "Robo"], ["Brute", "Snail", "Dragon Turtle"], ["Fiend"], [], [], ["Witch", "Witch", "Dino", "Witch"], [], [], [], [], ["Centaur", "Centaur", "Centaur", "Centaur", "Pack Leader", "Brute", "Brute", "Brute", "Brute"]], "mercenariesReceivedPerWave": [[], ["Dragon Turtle"], ["Snail"], ["Snail"], ["Lizard"], ["Dino"], ["Fiend"], ["Dragon Turtle", "Snail"], ["Fiend"], ["Dragon Turtle", "Dragon Turtle", "Dragon Turtle"], ["Dino"], [], [], ["Pack Leader", "Safety Mole", "Hermit", "Robo"], ["Drake", "Lizard"], ["Drake", "Hermit", "Dino"]], "leaksPerWave": [[], [], [], [], [], [], [], [], [], [], [], [], [], ["Killer Slug", "Killer Slug", "Killer Slug", "Killer Slug", "Killer Slug", "Robo", "Hermit", "Safety Mole", "Pack Leader"], [], ["Cardinal", "Cardinal", "Cardinal", "Cardinal", "Cardinal", "Cardinal", "Hermit", "Drake"]], "buildPerWave": [["priestess_of_the_abyss_unit_id:0.5|10.5:0"], ["priestess_of_the_abyss_unit_id:0.5|10.5:0"], ["priestess_of_the_abyss_unit_id:0.5|10.5:0"], ["priestess_of_the_abyss_unit_id:0.5|10.5:0", "golden_buckler_unit_id:2.5|6.5:0", "golden_buckler_unit_id:8.5|6:0"], ["priestess_of_the_abyss_unit_id:0.5|10.5:0", "golden_buckler_unit_id:2.5|6.5:0", "golden_buckler_unit_id:8.5|6:0", "golden_buckler_unit_id:0.5|6.5:0", "gargoyle_unit_id:8.5|5:0"], ["priestess_of_the_abyss_unit_id:0.5|10.5:0", "royal_guard_unit_id:2.5|6.5:0", "golden_buckler_unit_id:8.5|6:0", "golden_buckler_unit_id:0.5|6.5:0", "gargoyle_unit_id:8.5|5:0", "chained_fist_unit_id:8.5|4:0"], ["priestess_of_the_abyss_unit_id:0.5|10.5:0", "royal_guard_unit_id:2.5|6.5:0", "golden_buckler_unit_id:8.5|6:0", "golden_buckler_unit_id:0.5|6.5:0", "gargoyle_unit_id:8.5|5:0", "chained_fist_unit_id:8.5|4:0", "elite_archer_unit_id:0.5|8.5:0", "chained_fist_unit_id:8.5|3:0"], ["priestess_of_the_abyss_unit_id:0.5|10.5:0", "royal_guard_unit_id:2.5|6.5:0", "golden_buckler_unit_id:8.5|6:0", "golden_buckler_unit_id:0.5|6.5:0", "gargoyle_unit_id:8.5|5:0", "chained_fist_unit_id:8.5|4:0", "elite_archer_unit_id:0.5|8.5:0", "chained_fist_unit_id:8.5|3:0", "gargoyle_unit_id:3.5|6:0", "gargoyle_unit_id:1.5|6:0", "gargoyle_unit_id:2.5|5.5:0", "chained_fist_unit_id:8.5|2:0"], ["priestess_of_the_abyss_unit_id:0.5|10.5:0", "royal_guard_unit_id:2.5|6.5:0", "royal_guard_unit_id:8.5|6:0", "golden_buckler_unit_id:0.5|6.5:0", "gargoyle_unit_id:8.5|5:0", "chained_fist_unit_id:8.5|4:0", "elite_archer_unit_id:0.5|8.5:0", "chained_fist_unit_id:8.5|3:0", "gargoyle_unit_id:3.5|6:0", "gargoyle_unit_id:1.5|6:0", "gargoyle_unit_id:2.5|5.5:0", "chained_fist_unit_id:8.5|2:0", "golden_buckler_unit_id:4.5|5.5:0"], ["priestess_of_the_abyss_unit_id:0.5|10.5:0", "royal_guard_unit_id:2.5|6.5:0", "royal_guard_unit_id:8.5|6:0", "golden_buckler_unit_id:0.5|6.5:0", "gargoyle_unit_id:8.5|5:0", "chained_fist_unit_id:8.5|4:0", "elite_archer_unit_id:0.5|8.5:0", "chained_fist_unit_id:8.5|3:0", "gargoyle_unit_id:3.5|6:0", "gargoyle_unit_id:1.5|6:0", "gargoyle_unit_id:2.5|5.5:0", "chained_fist_unit_id:8.5|2:0", "golden_buckler_unit_id:4.5|5.5:0", "chained_fist_unit_id:8.5|1:0", "disciple_unit_id:1.5|10:0"], ["priestess_of_the_abyss_unit_id:0.5|10.5:0", "royal_guard_unit_id:2.5|6.5:0", "royal_guard_unit_id:8.5|6:0", "royal_guard_unit_id:0.5|6.5:0", "gargoyle_unit_id:8.5|5:0", "chained_fist_unit_id:8.5|4:0", "elite_archer_unit_id:0.5|8.5:0", "chained_fist_unit_id:8.5|3:0", "gargoyle_unit_id:3.5|6:0", "gargoyle_unit_id:1.5|6:0", "gargoyle_unit_id:2.5|5.5:0", "chained_fist_unit_id:8.5|2:0", "royal_guard_unit_id:4.5|5.5:0", "chained_fist_unit_id:8.5|1:0", "disciple_unit_id:1.5|10:0"], ["azeria_unit_id:0.5|10.5:0", "royal_guard_unit_id:2.5|6.5:0", "royal_guard_unit_id:8.5|6:0", "royal_guard_unit_id:0.5|6.5:0", "gargoyle_unit_id:8.5|5:0", "chained_fist_unit_id:8.5|4:0", "elite_archer_unit_id:0.5|8.5:0", "chained_fist_unit_id:8.5|3:0", "gargoyle_unit_id:3.5|6:0", "gargoyle_unit_id:1.5|6:0", "gargoyle_unit_id:2.5|5.5:0", "chained_fist_unit_id:8.5|2:0", "royal_guard_unit_id:4.5|5.5:0", "chained_fist_unit_id:8.5|1:0", "disciple_unit_id:1.5|10:0", "gargoyle_unit_id:7.5|5.5:0"], ["azeria_unit_id:0.5|10.5:0", "royal_guard_unit_id:2.5|6.5:0", "royal_guard_unit_id:8.5|6:0", "royal_guard_unit_id:0.5|6.5:0", "gargoyle_unit_id:8.5|5:0", "chained_fist_unit_id:8.5|4:0", "elite_archer_unit_id:0.5|8.5:0", "chained_fist_unit_id:8.5|3:0", "green_devil_unit_id:3.5|6:0", "gargoyle_unit_id:1.5|6:0", "gargoyle_unit_id:2.5|5.5:0", "chained_fist_unit_id:8.5|2:0", "royal_guard_unit_id:4.5|5.5:0", "chained_fist_unit_id:8.5|1:0", "disciple_unit_id:1.5|10:0", "gargoyle_unit_id:7.5|5.5:0", "priestess_of_the_abyss_unit_id:2.5|9.5:0", "gargoyle_unit_id:7.5|4.5:0", "gargoyle_unit_id:7.5|3.5:0"], ["azeria_unit_id:0.5|10.5:0", "royal_guard_unit_id:2.5|6.5:0", "royal_guard_unit_id:8.5|6:0", "royal_guard_unit_id:0.5|6.5:0", "gargoyle_unit_id:8.5|5:0", "chained_fist_unit_id:8.5|4:0", "elite_archer_unit_id:0.5|8.5:0", "chained_fist_unit_id:8.5|3:0", "green_devil_unit_id:3.5|6:0", "green_devil_unit_id:1.5|6:0", "gargoyle_unit_id:2.5|5.5:0", "chained_fist_unit_id:8.5|2:0", "royal_guard_unit_id:4.5|5.5:0", "chained_fist_unit_id:8.5|1:0", "starcaller_unit_id:1.5|10:0", "gargoyle_unit_id:7.5|5.5:0", "priestess_of_the_abyss_unit_id:2.5|9.5:0", "gargoyle_unit_id:7.5|4.5:0", "gargoyle_unit_id:7.5|3.5:0", "gargoyle_unit_id:4.5|6.5:0"], ["azeria_unit_id:0.5|10.5:0", "royal_guard_unit_id:2.5|6.5:0", "royal_guard_unit_id:8.5|6:0", "royal_guard_unit_id:0.5|6.5:0", "gargoyle_unit_id:8.5|5:0", "chained_fist_unit_id:8.5|4:0", "elite_archer_unit_id:0.5|8.5:0", "chained_fist_unit_id:8.5|3:0", "green_devil_unit_id:3.5|6:0", "green_devil_unit_id:1.5|6:0", "gargoyle_unit_id:2.5|5.5:0", "royal_guard_unit_id:4.5|5.5:0", "starcaller_unit_id:1.5|10:0", "green_devil_unit_id:7.5|5.5:0", "priestess_of_the_abyss_unit_id:2.5|9.5:0", "gargoyle_unit_id:7.5|4.5:0", "gargoyle_unit_id:7.5|3.5:0", "gargoyle_unit_id:4.5|6.5:0", "priestess_of_the_abyss_unit_id:2.5|10.5:0"], ["azeria_unit_id:0.5|10.5:0", "royal_guard_unit_id:2.5|6.5:0", "royal_guard_unit_id:8.5|6:0", "royal_guard_unit_id:0.5|6.5:0", "gargoyle_unit_id:8.5|5:0", "chained_fist_unit_id:8.5|4:0", "elite_archer_unit_id:0.5|8.5:0", "chained_fist_unit_id:8.5|3:0", "green_devil_unit_id:3.5|6:0", "green_devil_unit_id:1.5|6:0", "gargoyle_unit_id:2.5|5.5:0", "royal_guard_unit_id:4.5|5.5:0", "starcaller_unit_id:1.5|10:0", "green_devil_unit_id:7.5|5.5:0", "azeria_unit_id:2.5|9.5:0", "gargoyle_unit_id:7.5|4.5:0", "gargoyle_unit_id:7.5|3.5:0", "gargoyle_unit_id:4.5|6.5:0", "priestess_of_the_abyss_unit_id:2.5|10.5:0", "disciple_unit_id:1.5|11:0", "golden_buckler_unit_id:0.5|5.5:0", "golden_buckler_unit_id:1.5|5:0", "golden_buckler_unit_id:0.5|4.5:0"]], "leakValue": 224, "leaksCaughtValue": 186, "leftAtSeconds": -1, "kingUpgradesPerWave": [["Upgrade King Attack"], [], [], [], [], [], [], [], [], [], [], [], [], [], [], []], "opponentKingUpgradesPerWave": [[], ["Upgrade King Spell"], ["Upgrade King Attack"], ["Upgrade King Spell"], ["Upgrade King Regen"], ["Upgrade King Attack"], ["Upgrade King Regen"], ["Upgrade King Regen", "Upgrade King Regen"], ["Upgrade King Attack", "Upgrade King Attack", "Upgrade King Spell"], ["Upgrade King Attack", "Upgrade King Attack", "Upgrade King Attack"], ["Upgrade King Attack", "Upgrade King Spell", "Upgrade King Spell"], ["Upgrade King Attack", "Upgrade King Attack", "Upgrade King Regen", "Upgrade King Regen", "Upgrade King Regen"], [], [], [], []], "megamind": true, "chosenChampionLocation": "0.5|10.5"}, {"playerId": "9DAE2CCE11E04B12", "playerName": "Flittermouse", "playerSlot": 2, "legion": "Chaos", "workers": 42.64533, "value": 3845, "cross": false, "gameResult": "won", "classicElo": 2457, "overallElo": 2276, "eloChange": 12, "fighters": "Bone Warrior,Dark Mage,Shadow Dancer,Shadow Dancer,Cursed Casket,Butcher,Fenix,Sacred Steed,Sovereign,Eternal Wanderer,Windhawk,Daphne,Leviathan,Desert Pilgrim,Orchid,Hell Raiser,Cursed Casket", "eco": false, "mercenaries": "Snail,Fiend,Fiend,Fiend,Lizard,Lizard,Lizard,Fiend,Cannoneer,Ghost Knight,Four Eyes,Fiend,Robo,Robo,Needler,Needler,Shaman,Pack Leader,Safety Mole,Hermit,Snail", "stayedUntilEnd": true, "chosenSpell": "Press the Attack", "chosenSpellLocation": "-1|-1", "partySize": 2, "firstWaveFighters": "Masked Spirit,Cursed Casket", "rolls": "", "legionSpecificElo": 2156, "partyMembers": ["Stars", "Flittermouse"], "partyMembersIds": ["906C137BD0F81FD9", "9DAE2CCE11E04B12"], "mvpScore": 6315, "netWorthPerWave": [448, 566, 708, 900, 1140, 1406, 1692, 1972, 2246, 2620, 3322, 3811, 4297, 4895, 5705, 6226], "valuePerWave": [155, 175, 215, 295, 500, 680, 800, 890, 1155, 1345, 1520, 1855, 2280, 2840, 3195, 3845], "workersPerWave": [5, 7, 8, 8, 9, 11, 14, 16, 18, 21, 25.365335, 30.325335, 30.325335, 36.245335, 42.64533, 42.64533], "incomePerWave": [10, 28, 46, 64, 88, 118, 148, 148, 148, 208, 306, 306, 306, 306, 576, 662], "mercenariesSentPerWave": [["Snail"], [], ["Fiend"], ["Fiend"], ["Fiend"], ["Lizard", "Lizard", "Lizard"], ["Fiend"], ["Cannoneer"], [], [], ["Ghost Knight", "Four Eyes", "Robo", "Robo", "Fiend"], [], [], [], [], ["Pack Leader", "Safety Mole", "Hermit", "Needler", "Needler", "Shaman", "Snail"]], "mercenariesReceivedPerWave": [["Snail"], ["Snail"], ["Snail"], [], ["Hermit", "Snail"], ["Lizard", "Lizard", "Snail"], ["Fiend"], [], ["Safety Mole", "Brute", "Snail"], ["Hermit", "Lizard", "Snail"], ["Snail", "Snail"], ["Snail", "Snail", "Snail", "Snail", "Snail"], [], ["Four Eyes", "Hermit", "Dragon Turtle"], ["Drake", "Dino"], ["Safety Mole", "Hermit", "Lizard", "Lizard", "Lizard"]], "leaksPerWave": [[], [], [], [], [], [], [], [], ["Carapace", "Carapace", "Carapace", "Carapace", "Brute", "Safety Mole"], ["Granddaddy"], [], [], [], [], [], []], "buildPerWave": [["cursed_casket_unit_id:2.5|4.5:0", "masked_spirit_unit_id:0.5|9.5:0"], ["cursed_casket_unit_id:2.5|4.5:0", "masked_spirit_unit_id:0.5|9.5:0", "looter_unit_id:0.5|4.5:0", "looter_unit_id:0.5|3.5:0"], ["cursed_casket_unit_id:2.5|4.5:0", "masked_spirit_unit_id:0.5|9.5:0", "looter_unit_id:0.5|4.5:0", "looter_unit_id:0.5|3.5:0", "gargoyle_unit_id:0.5|5.5:0"], ["cursed_casket_unit_id:2.5|4.5:0", "masked_spirit_unit_id:0.5|9.5:0", "looter_unit_id:0.5|4.5:0", "looter_unit_id:0.5|3.5:0", "gargoyle_unit_id:0.5|5.5:0", "infiltrator_unit_id:3.5|4:0"], ["cursed_casket_unit_id:2.5|4.5:0", "false_maiden_unit_id:0.5|9.5:0", "looter_unit_id:0.5|4.5:0", "looter_unit_id:0.5|3.5:0", "gargoyle_unit_id:0.5|5.5:0", "infiltrator_unit_id:3.5|4:0", "desert_pilgrim_unit_id:1.5|7:0"], ["cursed_casket_unit_id:2.5|4.5:0", "false_maiden_unit_id:0.5|9.5:0", "gargoyle_unit_id:0.5|5.5:0", "orchid_unit_id:3.5|4:0", "desert_pilgrim_unit_id:1.5|7:0"], ["cursed_casket_unit_id:2.5|4.5:0", "hell_raiser_unit_id:0.5|9.5:0", "gargoyle_unit_id:0.5|5.5:0", "orchid_unit_id:3.5|4:0", "desert_pilgrim_unit_id:1.5|7:0"], ["cursed_casket_unit_id:2.5|4.5:0", "hell_raiser_buffed_unit_id:0.5|9.5:1", "gargoyle_unit_id:0.5|5.5:0", "orchid_unit_id:3.5|4:0", "desert_pilgrim_unit_id:1.5|7:0", "tempest_unit_id:0.5|8.5:0"], ["cursed_casket_unit_id:2.5|4.5:0", "hell_raiser_unit_id:0.5|9.5:0", "gargoyle_unit_id:0.5|5.5:0", "orchid_unit_id:3.5|4:0", "desert_pilgrim_unit_id:1.5|7:0", "tempest_unit_id:0.5|8.5:0", "daphne_unit_id:0.5|6.5:0", "windhawk_unit_id:4.5|3.5:0"], ["cursed_casket_unit_id:2.5|4.5:0", "hell_raiser_buffed_unit_id:0.5|9.5:1", "gargoyle_unit_id:0.5|5.5:0", "orchid_unit_id:3.5|4:0", "desert_pilgrim_unit_id:1.5|7:0", "leviathan_unit_id:0.5|8.5:0", "daphne_unit_id:0.5|6.5:0", "windhawk_unit_id:4.5|3.5:0"], ["cursed_casket_unit_id:2.5|4.5:0", "hell_raiser_unit_id:0.5|9.5:0", "gargoyle_unit_id:0.5|5.5:0", "orchid_unit_id:3.5|4:9", "desert_pilgrim_unit_id:1.5|7:0", "leviathan_unit_id:0.5|8.5:0", "daphne_unit_id:0.5|6.5:0", "windhawk_unit_id:4.5|3.5:0", "eternal_wanderer_unit_id:8.5|9.5:0", "howler_unit_id:8.5|8.5:0"], ["cursed_casket_unit_id:2.5|4.5:0", "hell_raiser_buffed_unit_id:0.5|9.5:1", "gargoyle_unit_id:0.5|5.5:0", "orchid_unit_id:3.5|4:0", "desert_pilgrim_unit_id:1.5|7:0", "leviathan_unit_id:0.5|8.5:0", "daphne_unit_id:0.5|6.5:0", "windhawk_unit_id:4.5|3.5:0", "eternal_wanderer_unit_id:8.5|9.5:0", "howler_unit_id:8.5|8.5:0", "holy_avenger_unit_id:2.5|3.5:0", "sacred_steed_unit_id:4.5|4.5:0"], ["cursed_casket_unit_id:2.5|4.5:0", "hell_raiser_unit_id:0.5|9.5:0", "gargoyle_unit_id:0.5|5.5:0", "orchid_unit_id:3.5|4:0", "desert_pilgrim_unit_id:1.5|7:0", "leviathan_unit_id:0.5|8.5:0", "daphne_unit_id:0.5|6.5:0", "windhawk_unit_id:4.5|3.5:0", "eternal_wanderer_unit_id:8.5|9.5:0", "howler_unit_id:8.5|8.5:0", "holy_avenger_unit_id:2.5|3.5:0", "sacred_steed_unit_id:4.5|4.5:0", "fire_lord_unit_id:1.5|9:0", "butcher_unit_id:3.5|3:0"], ["cursed_casket_unit_id:2.5|4.5:0", "hell_raiser_buffed_unit_id:0.5|9.5:1", "gargoyle_unit_id:0.5|5.5:0", "orchid_unit_id:3.5|4:0", "desert_pilgrim_unit_id:1.5|7:0", "leviathan_unit_id:0.5|8.5:0", "daphne_unit_id:0.5|6.5:0", "windhawk_unit_id:4.5|3.5:0", "eternal_wanderer_unit_id:8.5|9.5:0", "howler_unit_id:8.5|8.5:0", "sovereign_unit_id:2.5|3.5:0", "sacred_steed_unit_id:4.5|4.5:0", "fire_lord_unit_id:1.5|9:0", "butcher_unit_id:3.5|3:0", "cursed_casket_unit_id:4.5|2.5:0"], ["cursed_casket_unit_id:2.5|4.5:0", "hell_raiser_unit_id:0.5|9.5:0", "orchid_unit_id:3.5|4:0", "desert_pilgrim_unit_id:1.5|7:0", "leviathan_unit_id:0.5|8.5:0", "daphne_unit_id:0.5|6.5:0", "windhawk_unit_id:4.5|3.5:0", "eternal_wanderer_unit_id:8.5|9.5:0", "sovereign_unit_id:2.5|3.5:0", "sacred_steed_unit_id:4.5|4.5:0", "fenix_unit_id:1.5|9:0", "butcher_unit_id:3.5|3:0", "cursed_casket_unit_id:4.5|2.5:0"], ["cursed_casket_unit_id:2.5|4.5:0", "hell_raiser_buffed_unit_id:0.5|9.5:1", "orchid_unit_id:3.5|4:0", "desert_pilgrim_unit_id:1.5|7:0", "leviathan_unit_id:0.5|8.5:0", "daphne_unit_id:0.5|6.5:0", "windhawk_unit_id:4.5|3.5:0", "eternal_wanderer_unit_id:8.5|9.5:0", "sovereign_unit_id:2.5|3.5:0", "sacred_steed_unit_id:4.5|4.5:0", "fenix_unit_id:1.5|9:0", "butcher_unit_id:3.5|3:0", "cursed_casket_unit_id:4.5|2.5:0", "shadow_dancer_unit_id:2.5|2.5:0", "shadow_dancer_unit_id:3.5|2:0", "dark_mage_unit_id:0.5|4.5:0", "bone_warrior_unit_id:8.5|7.5:0"]], "leakValue": 94, "leaksCaughtValue": 60, "leftAtSeconds": -1, "kingUpgradesPerWave": [[], [], [], [], [], [], [], [], [], [], [], [], [], [], [], []], "opponentKingUpgradesPerWave": [[], ["Upgrade King Spell"], ["Upgrade King Spell"], [], [], [], ["Upgrade King Regen"], [], [], [], ["Upgrade King Spell", "Upgrade King Spell", "Upgrade King Spell"], ["Upgrade King Regen", "Upgrade King Regen"], [], [], [], []], "megamind": false, "chosenChampionLocation": "-1|-1"}, {"playerId": "DFF8AB1D782FAF76", "playerName": "miw1214", "playerSlot": 5, "legion": "Kingsguard", "workers": 24.6608, "value": 4495, "cross": false, "gameResult": "lost", "classicElo": 1849, "overallElo": 1993, "eloChange": -12, "fighters": "Windhawk,Violet,Violet,Green Devil,Green Devil,Green Devil,Green Devil,Green Devil,Green Devil,Green Devil,Green Devil,Fire Archer,Dark Mage,Violet,Violet,Arc Of Justice,Starcaller,Dark Mage,Bone Crusher,Fire Archer,Green Devil,Violet,Bone Crusher", "eco": false, "mercenaries": "Snail,Snail,Snail,Hermit,Snail,Lizard,Lizard,Snail,Fiend,Safety Mole,Brute,Snail,Hermit,Lizard,Snail,Snail,Snail,Snail,Snail,Snail,Snail,Snail,Four Eyes,Hermit,Dragon Turtle,Drake,Dino,Safety Mole,Hermit,Lizard,Lizard,Lizard", "stayedUntilEnd": true, "chosenSpell": "Pawn Shop", "chosenSpellLocation": "-1|-1", "partySize": 2, "firstWaveFighters": "Bone Crusher", "rolls": "bone_warrior_unit_id, gargoyle_unit_id, windhawk_unit_id, disciple_unit_id, radiant_halo_unit_id, banana_bunk_unit_id", "legionSpecificElo": 1622, "partyMembers": ["miw1214", "LIFE1"], "partyMembersIds": ["DFF8AB1D782FAF76", "90B22B86F9E22534"], "mvpScore": 3766, "netWorthPerWave": [447, 570, 693, 834, 1030, 1257, 1523, 1822, 2226, 2632, 3159, 3601, 4127, 4970, 5650, 6010], "valuePerWave": [110, 195, 250, 330, 425, 575, 755, 950, 1150, 1575, 2025, 2025, 2440, 2975, 3815, 4495], "workersPerWave": [5, 6, 7, 8, 9, 10, 11, 13, 13, 13, 15.24, 24.6608, 24.6608, 24.6608, 24.6608, 24.6608], "incomePerWave": [15, 27, 33, 53, 83, 107, 113, 149, 184, 214, 262, 274, 346, 426, 476, 512], "mercenariesSentPerWave": [["Snail"], ["Snail"], ["Snail"], [], ["Hermit", "Snail"], ["Lizard", "Lizard", "Snail"], ["Fiend"], [], ["Safety Mole", "Snail", "Brute"], ["Hermit", "Lizard", "Snail"], ["Snail", "Snail"], ["Snail", "Snail", "Snail", "Snail", "Snail"], [], ["Four Eyes", "Dragon Turtle", "Hermit"], ["Drake", "Dino"], ["Safety Mole", "Hermit", "Lizard", "Lizard", "Lizard"]], "mercenariesReceivedPerWave": [[], ["Snail", "Snail"], [], ["Robo", "Robo", "Snail"], ["Robo", "Snail"], ["Robo", "Robo", "Robo"], ["Brute", "Dragon Turtle", "Snail"], ["Fiend"], [], [], ["Witch", "Witch", "Witch", "Dino"], [], [], [], [], ["Centaur", "Centaur", "Centaur", "Centaur", "Pack Leader", "Brute", "Brute", "Brute", "Brute"]], "leaksPerWave": [[], [], [], ["Flying Chicken", "Flying Chicken", "Flying Chicken", "Flying Chicken", "Flying Chicken", "Robo", "Robo", "Flying Chicken"], ["Scorpion", "Scorpion", "Robo"], ["Rocko", "Robo", "Robo", "Robo"], [], [], [], [], ["Froggo", "Quill Shooter", "Quill Shooter", "Quill Shooter", "Quill Shooter", "Quill Shooter", "Witch", "Witch", "Witch"], [], [], [], [], ["Cardinal", "Cardinal", "Cardinal", "Cardinal", "Cardinal", "Cardinal", "Cardinal", "Cardinal", "Cardinal", "Cardinal", "Cardinal", "Cardinal", "Brute", "Brute", "Brute", "Pack Leader", "Centaur", "Centaur", "Centaur"]], "buildPerWave": [["bone_crusher_unit_id:1.5|4.5:0"], ["bone_crusher_unit_id:1.5|4.5:0", "windhawk_unit_id:2.5|2:0"], ["bone_crusher_unit_id:1.5|4.5:0", "windhawk_unit_id:2.5|2:0", "gargoyle_unit_id:2.5|4:0", "bone_warrior_unit_id:7.5|4.5:0"], ["bone_crusher_unit_id:1.5|4.5:0", "windhawk_unit_id:2.5|2:0", "gargoyle_unit_id:2.5|4:0", "bone_warrior_unit_id:7.5|4.5:0", "fire_archer_unit_id:0.5|2:0"], ["bone_crusher_unit_id:1.5|4.5:0", "windhawk_unit_id:2.5|2:0", "gargoyle_unit_id:2.5|4:0", "bone_crusher_unit_id:7.5|4.5:0", "fire_archer_unit_id:0.5|2:0"], ["bone_crusher_unit_id:1.5|4.5:0", "windhawk_unit_id:2.5|2:0", "green_devil_unit_id:2.5|4:0", "bone_crusher_unit_id:7.5|4.5:0", "fire_archer_unit_id:0.5|2:0", "bone_warrior_unit_id:8.5|4:0", "bone_warrior_unit_id:1.5|0.5:0"], ["bone_crusher_unit_id:1.5|4.5:0", "violet_unit_id:2.5|2:0", "green_devil_unit_id:2.5|4:0", "bone_crusher_unit_id:7.5|4.5:0", "fire_archer_unit_id:0.5|2:0", "bone_warrior_unit_id:8.5|4:0", "bone_warrior_unit_id:1.5|0.5:0"], ["bone_crusher_unit_id:1.5|4.5:0", "violet_unit_id:2.5|2:0", "green_devil_unit_id:2.5|4:0", "bone_crusher_unit_id:7.5|4.5:0", "fire_archer_unit_id:0.5|2:0", "bone_warrior_unit_id:8.5|4:0", "bone_warrior_unit_id:1.5|0.5:0", "disciple_unit_id:1.5|1.5:0"], ["bone_crusher_unit_id:1.5|4.5:0", "violet_unit_id:2.5|2:0", "green_devil_unit_id:2.5|4:0", "bone_crusher_unit_id:7.5|4.5:0", "fire_archer_unit_id:0.5|2:0", "bone_warrior_unit_id:8.5|4:0", "bone_warrior_unit_id:1.5|0.5:0", "disciple_unit_id:1.5|1.5:0", "radiant_halo_unit_id:2.5|1:0"], ["bone_crusher_unit_id:1.5|4.5:0", "violet_unit_id:2.5|2:0", "green_devil_unit_id:2.5|4:0", "bone_crusher_unit_id:7.5|4.5:0", "fire_archer_unit_id:0.5|2:0", "bone_warrior_unit_id:8.5|4:0", "dark_mage_unit_id:1.5|0.5:0", "disciple_unit_id:1.5|1.5:0", "arc_of_justice_unit_id:2.5|1:0"], ["bone_crusher_unit_id:1.5|4.5:0", "violet_unit_id:2.5|2:0", "green_devil_unit_id:2.5|4:0", "fire_archer_unit_id:0.5|2:0", "bone_warrior_unit_id:8.5|4:0", "dark_mage_unit_id:1.5|0.5:0", "disciple_unit_id:1.5|1.5:0", "arc_of_justice_unit_id:2.5|1:0", "violet_unit_id:1.5|2.5:0", "violet_unit_id:0.5|1:0", "bone_warrior_unit_id:8.5|6:0", "bone_warrior_unit_id:8.5|8:0"], ["bone_crusher_unit_id:1.5|4.5:0", "violet_unit_id:2.5|2:0", "green_devil_unit_id:2.5|4:0", "fire_archer_unit_id:0.5|2:0", "bone_warrior_unit_id:8.5|4:0", "dark_mage_unit_id:1.5|0.5:0", "disciple_unit_id:1.5|1.5:0", "arc_of_justice_unit_id:2.5|1:0", "violet_unit_id:1.5|2.5:0", "violet_unit_id:0.5|1:0", "bone_warrior_unit_id:8.5|6:0", "bone_warrior_unit_id:8.5|8:0"], ["bone_crusher_unit_id:1.5|4.5:0", "violet_unit_id:2.5|2:0", "green_devil_unit_id:2.5|4:0", "fire_archer_unit_id:0.5|2:0", "bone_warrior_unit_id:8.5|4:0", "dark_mage_unit_id:1.5|0.5:0", "starcaller_unit_id:1.5|1.5:0", "arc_of_justice_unit_id:2.5|1:0", "violet_unit_id:1.5|2.5:0", "violet_unit_id:0.5|1:0", "bone_warrior_unit_id:8.5|6:0", "bone_warrior_unit_id:8.5|8:0", "gargoyle_unit_id:0.5|4:0", "gargoyle_unit_id:2.5|3:0"], ["bone_crusher_unit_id:1.5|4.5:0", "violet_unit_id:2.5|2:0", "green_devil_unit_id:2.5|4:0", "fire_archer_unit_id:0.5|2:0", "bone_crusher_unit_id:8.5|4:0", "dark_mage_unit_id:1.5|0.5:0", "starcaller_unit_id:1.5|1.5:0", "arc_of_justice_unit_id:2.5|1:0", "violet_unit_id:1.5|2.5:0", "violet_unit_id:0.5|1:0", "bone_warrior_unit_id:8.5|6:0", "bone_warrior_unit_id:8.5|8:0", "green_devil_unit_id:0.5|4:0", "green_devil_unit_id:2.5|3:0", "gargoyle_unit_id:0.5|3:0", "green_devil_unit_id:3.5|4.5:0"], ["bone_crusher_unit_id:1.5|4.5:0", "violet_unit_id:2.5|2:0", "green_devil_unit_id:2.5|4:0", "fire_archer_unit_id:0.5|2:0", "bone_crusher_unit_id:8.5|4:0", "dark_mage_unit_id:1.5|0.5:0", "starcaller_unit_id:1.5|1.5:0", "arc_of_justice_unit_id:2.5|1:0", "violet_unit_id:1.5|2.5:0", "violet_unit_id:0.5|1:0", "dark_mage_unit_id:8.5|6:0", "bone_warrior_unit_id:8.5|8:0", "green_devil_unit_id:0.5|4:0", "green_devil_unit_id:2.5|3:0", "green_devil_unit_id:0.5|3:0", "green_devil_unit_id:3.5|4.5:0", "green_devil_unit_id:4.5|4:0", "green_devil_unit_id:4.5|3:0", "green_devil_unit_id:0.5|5:0", "green_devil_unit_id:2.5|5:0"], ["bone_crusher_unit_id:1.5|4.5:0", "violet_unit_id:2.5|2:0", "green_devil_unit_id:2.5|4:0", "fire_archer_unit_id:0.5|2:0", "bone_crusher_unit_id:8.5|4:0", "dark_mage_unit_id:1.5|0.5:0", "starcaller_unit_id:1.5|1.5:0", "arc_of_justice_unit_id:2.5|1:0", "violet_unit_id:1.5|2.5:0", "violet_unit_id:0.5|1:0", "dark_mage_unit_id:8.5|6:0", "fire_archer_unit_id:8.5|8:0", "green_devil_unit_id:0.5|4:0", "green_devil_unit_id:2.5|3:0", "green_devil_unit_id:0.5|3:0", "green_devil_unit_id:3.5|4.5:0", "green_devil_unit_id:4.5|4:0", "green_devil_unit_id:4.5|3:0", "green_devil_unit_id:0.5|5:0", "green_devil_unit_id:2.5|5:0", "violet_unit_id:5.5|1:0", "violet_unit_id:3.5|2:0", "windhawk_unit_id:5.5|2:0"]], "leakValue": 227, "leaksCaughtValue": 60, "leftAtSeconds": -1, "kingUpgradesPerWave": [[], ["Upgrade King Spell"], ["Upgrade King Spell"], [], [], [], ["Upgrade King Regen"], [], [], [], ["Upgrade King Spell", "Upgrade King Spell", "Upgrade King Spell"], ["Upgrade King Regen", "Upgrade King Regen"], [], [], [], []], "opponentKingUpgradesPerWave": [["Upgrade King Attack"], [], [], [], [], [], [], [], [], [], [], [], [], [], [], []], "megamind": false, "chosenChampionLocation": "-1|-1"}, {"playerId": "90B22B86F9E22534", "playerName": "LIFE1", "playerSlot": 6, "legion": "Fiesta", "workers": 21.495432, "value": 4840, "cross": false, "gameResult": "lost", "classicElo": 3261, "overallElo": 2090, "eloChange": -12, "fighters": "Royal Guard,Vulcan Cannon,Shadow Dancer,Treant,Shadow Dancer,Shadow Dancer,APS,Shadow Dancer,Royal Guard,Royal Guard,Dread Knight,MPS,Sovereign,Pollywog,Tree Of Life,Pollywog,Devilfish,Devilfish,Pollywog,Pollywog,Devilfish", "eco": false, "mercenaries": "Dragon Turtle,Snail,Snail,Lizard,Dino,Fiend,Dragon Turtle,Snail,Fiend,Dragon Turtle,Dragon Turtle,Dragon Turtle,Dino,Pack Leader,Safety Mole,Hermit,Robo,Drake,Lizard,Drake,Hermit,Dino", "stayedUntilEnd": true, "chosenSpell": "Pawn Shop", "chosenSpellLocation": "-1|-1", "partySize": 2, "firstWaveFighters": "Pollywog,Devilfish", "rolls": "pollywog_unit_id, treant_unit_id, aps_unit_id, gatling_gun_unit_id, disciple_unit_id, holy_avenger_unit_id", "legionSpecificElo": 1523, "partyMembers": ["miw1214", "LIFE1"], "partyMembersIds": ["DFF8AB1D782FAF76", "90B22B86F9E22534"], "mvpScore": 4421, "netWorthPerWave": [433, 541, 685, 836, 1047, 1306, 1576, 1900, 2306, 2743, 3239, 3713, 4279, 5192, 5910, 6445], "valuePerWave": [110, 170, 285, 285, 365, 560, 830, 830, 980, 1410, 1915, 2185, 2585, 3225, 4125, 4840], "workersPerWave": [5, 5, 7, 9, 9, 9, 12, 16, 17, 17, 20.360003, 21.495432, 21.495432, 21.495432, 21.495432, 21.495432], "incomePerWave": [12, 24, 36, 54, 84, 108, 132, 162, 216, 258, 276, 306, 386, 454, 514, 534], "mercenariesSentPerWave": [[], ["Dragon Turtle"], ["Snail"], ["Snail"], ["Lizard"], ["Dino"], ["Fiend"], ["Dragon Turtle", "Snail"], ["Fiend"], ["Dragon Turtle", "Dragon Turtle", "Dragon Turtle"], ["Dino"], [], [], ["Pack Leader", "Safety Mole", "Robo", "Hermit"], ["Drake", "Lizard"], ["Drake", "Dino", "Hermit"]], "mercenariesReceivedPerWave": [["Snail"], [], ["Fiend"], ["Fiend"], ["Fiend"], ["Lizard", "Lizard", "Lizard"], ["Fiend"], ["Cannoneer"], [], [], ["Ghost Knight", "Four Eyes", "Fiend", "Robo", "Robo"], [], [], [], [], ["Needler", "Needler", "Shaman", "Pack Leader", "Safety Mole", "Hermit", "Snail"]], "leaksPerWave": [["Crab", "Crab", "Crab", "Crab", "Crab", "Crab", "Crab", "Crab", "Crab", "Crab"], [], [], ["Flying Chicken", "Flying Chicken", "Flying Chicken", "Flying Chicken", "Flying Chicken", "Flying Chicken", "Flying Chicken", "Flying Chicken", "Flying Chicken"], ["Scorpion", "Scorpion", "Fiend"], [], [], [], [], [], ["Quill Shooter", "Quill Shooter", "Quill Shooter", "Quill Shooter", "Quill Shooter", "Quill Shooter", "Quill Shooter", "Robo", "Robo", "Four Eyes", "Ghost Knight"], [], [], [], [], ["Cardinal", "Cardinal", "Cardinal", "Shaman", "Needler", "Needler"]], "buildPerWave": [["devilfish_unit_id:0.5|9.5:0", "pollywog_unit_id:8.5|9.5:0"], ["devilfish_unit_id:0.5|9.5:0", "pollywog_unit_id:8.5|9.5:0", "pollywog_unit_id:0.5|10.5:0", "pollywog_unit_id:1.5|10:0", "pollywog_unit_id:2.5|9.5:0", "pollywog_unit_id:7.5|9:0"], ["seraphin_unit_id:0.5|9.5:0", "pollywog_unit_id:8.5|9.5:0", "pollywog_unit_id:0.5|10.5:0", "pollywog_unit_id:1.5|10:0", "pollywog_unit_id:2.5|9.5:0", "pollywog_unit_id:7.5|9:0", "treant_unit_id:1.5|9:4", "pollywog_unit_id:2.5|8.5:0"], ["devilfish_unit_id:0.5|9.5:0", "pollywog_unit_id:8.5|9.5:0", "pollywog_unit_id:0.5|10.5:0", "pollywog_unit_id:1.5|10:0", "pollywog_unit_id:2.5|9.5:0", "pollywog_unit_id:7.5|9:0", "treant_unit_id:1.5|9:3", "pollywog_unit_id:2.5|8.5:0"], ["devilfish_unit_id:0.5|9.5:0", "pollywog_unit_id:8.5|9.5:0", "pollywog_unit_id:0.5|10.5:0", "seraphin_unit_id:1.5|10:0", "pollywog_unit_id:2.5|9.5:0", "pollywog_unit_id:7.5|9:0", "treant_unit_id:1.5|9:2", "pollywog_unit_id:2.5|8.5:0"], ["seraphin_unit_id:0.5|9.5:0", "pollywog_unit_id:8.5|9.5:0", "pollywog_unit_id:0.5|10.5:0", "seraphin_unit_id:1.5|10:0", "pollywog_unit_id:2.5|9.5:0", "pollywog_unit_id:7.5|9:0", "tree_of_life_unit_id:1.5|9:0", "pollywog_unit_id:2.5|8.5:0"], ["devilfish_unit_id:0.5|9.5:0", "pollywog_unit_id:8.5|9.5:0", "pollywog_unit_id:0.5|10.5:0", "devilfish_unit_id:1.5|10:0", "pollywog_unit_id:2.5|9.5:0", "pollywog_unit_id:7.5|9:0", "tree_of_life_unit_id:1.5|9:0", "pollywog_unit_id:2.5|8.5:0", "holy_avenger_unit_id:1.5|8:0"], ["seraphin_unit_id:0.5|9.5:0", "pollywog_unit_id:8.5|9.5:0", "pollywog_unit_id:0.5|10.5:0", "devilfish_unit_id:1.5|10:0", "pollywog_unit_id:2.5|9.5:0", "pollywog_unit_id:7.5|9:0", "tree_of_life_unit_id:1.5|9:0", "pollywog_unit_id:2.5|8.5:0", "holy_avenger_unit_id:1.5|8:0"], ["seraphin_unit_id:0.5|9.5:0", "pollywog_unit_id:8.5|9.5:0", "pollywog_unit_id:0.5|10.5:0", "seraphin_unit_id:1.5|10:0", "pollywog_unit_id:2.5|9.5:0", "pollywog_unit_id:7.5|9:0", "tree_of_life_unit_id:1.5|9:0", "pollywog_unit_id:2.5|8.5:0", "holy_avenger_unit_id:1.5|8:0", "aps_unit_id:1.5|7:0"], ["devilfish_unit_id:0.5|9.5:0", "pollywog_unit_id:8.5|9.5:0", "pollywog_unit_id:0.5|10.5:0", "devilfish_unit_id:1.5|10:0", "pollywog_unit_id:2.5|9.5:0", "pollywog_unit_id:7.5|9:0", "tree_of_life_unit_id:1.5|9:0", "pollywog_unit_id:2.5|8.5:0", "sovereign_unit_id:1.5|8:0", "aps_unit_id:1.5|7:0"], ["seraphin_unit_id:0.5|9.5:0", "pollywog_unit_id:8.5|9.5:0", "pollywog_unit_id:0.5|10.5:0", "seraphin_unit_id:1.5|10:0", "pollywog_unit_id:2.5|9.5:0", "pollywog_unit_id:7.5|9:0", "tree_of_life_unit_id:1.5|9:0", "pollywog_unit_id:2.5|8.5:0", "sovereign_unit_id:1.5|8:0", "aps_unit_id:1.5|7:0", "shadow_dancer_unit_id:0.5|7.5:0", "royal_guard_unit_id:3.5|8:0", "golden_buckler_unit_id:8.5|8.5:0"], ["seraphin_unit_id:0.5|9.5:0", "pollywog_unit_id:8.5|9.5:0", "pollywog_unit_id:0.5|10.5:0", "seraphin_unit_id:1.5|10:0", "pollywog_unit_id:2.5|9.5:0", "pollywog_unit_id:7.5|9:0", "tree_of_life_unit_id:1.5|9:0", "pollywog_unit_id:2.5|8.5:0", "sovereign_unit_id:1.5|8:0", "aps_unit_id:1.5|7:0", "shadow_dancer_unit_id:0.5|7.5:0", "royal_guard_unit_id:3.5|8:0", "golden_buckler_unit_id:8.5|8.5:0", "shadow_dancer_unit_id:2.5|7.5:0"], ["devilfish_unit_id:0.5|9.5:0", "pollywog_unit_id:8.5|9.5:0", "pollywog_unit_id:0.5|10.5:0", "devilfish_unit_id:1.5|10:0", "pollywog_unit_id:2.5|9.5:0", "pollywog_unit_id:7.5|9:0", "tree_of_life_unit_id:1.5|9:0", "pollywog_unit_id:2.5|8.5:0", "sovereign_unit_id:1.5|8:0", "mps_unit_id:1.5|7:0", "shadow_dancer_unit_id:0.5|7.5:0", "royal_guard_unit_id:3.5|8:0", "golden_buckler_unit_id:8.5|8.5:0", "shadow_dancer_unit_id:2.5|7.5:0", "aps_unit_id:0.5|8.5:0"], ["devilfish_unit_id:0.5|9.5:0", "pollywog_unit_id:8.5|9.5:0", "pollywog_unit_id:0.5|10.5:0", "devilfish_unit_id:1.5|10:0", "pollywog_unit_id:2.5|9.5:0", "pollywog_unit_id:7.5|9:0", "tree_of_life_unit_id:1.5|9:0", "pollywog_unit_id:2.5|8.5:0", "sovereign_unit_id:1.5|8:0", "mps_unit_id:1.5|7:0", "shadow_dancer_unit_id:0.5|7.5:0", "royal_guard_unit_id:3.5|8:0", "golden_buckler_unit_id:8.5|8.5:0", "shadow_dancer_unit_id:2.5|7.5:0", "aps_unit_id:0.5|8.5:0", "shadow_dancer_unit_id:2.5|6.5:0", "shadow_dancer_unit_id:0.5|6.5:0", "treant_unit_id:3.5|7:4"], ["devilfish_unit_id:0.5|9.5:0", "pollywog_unit_id:8.5|9.5:0", "pollywog_unit_id:0.5|10.5:0", "seraphin_unit_id:1.5|10:0", "seraphin_unit_id:2.5|9.5:0", "pollywog_unit_id:7.5|9:0", "tree_of_life_unit_id:1.5|9:0", "pollywog_unit_id:2.5|8.5:0", "sovereign_unit_id:1.5|8:0", "mps_unit_id:1.5|7:0", "dread_knight_unit_id:0.5|7.5:0", "royal_guard_unit_id:3.5|8:0", "royal_guard_unit_id:8.5|8.5:0", "shadow_dancer_unit_id:2.5|7.5:0", "aps_unit_id:0.5|8.5:0", "shadow_dancer_unit_id:2.5|6.5:0", "shadow_dancer_unit_id:0.5|6.5:0", "treant_unit_id:3.5|7:3", "shadow_dancer_unit_id:1.5|6:0"], ["devilfish_unit_id:0.5|9.5:0", "pollywog_unit_id:8.5|9.5:0", "pollywog_unit_id:0.5|10.5:0", "devilfish_unit_id:1.5|10:0", "devilfish_unit_id:2.5|9.5:0", "pollywog_unit_id:7.5|9:0", "tree_of_life_unit_id:1.5|9:0", "pollywog_unit_id:2.5|8.5:0", "sovereign_unit_id:1.5|8:0", "mps_unit_id:1.5|7:0", "dread_knight_unit_id:0.5|7.5:0", "royal_guard_unit_id:3.5|8:0", "royal_guard_unit_id:8.5|8.5:0", "shadow_dancer_unit_id:2.5|7.5:0", "aps_unit_id:0.5|8.5:0", "shadow_dancer_unit_id:2.5|6.5:0", "shadow_dancer_unit_id:0.5|6.5:0", "treant_unit_id:3.5|7:2", "shadow_dancer_unit_id:1.5|6:0", "vulcan_cannon_unit_id:1.5|11:0", "royal_guard_unit_id:3.5|9:0"]], "leakValue": 355, "leaksCaughtValue": 0, "leftAtSeconds": -1, "kingUpgradesPerWave": [[], ["Upgrade King Spell"], ["Upgrade King Attack"], ["Upgrade King Spell"], ["Upgrade King Regen"], ["Upgrade King Attack"], ["Upgrade King Regen"], ["Upgrade King Regen", "Upgrade King Regen"], ["Upgrade King Attack", "Upgrade King Attack", "Upgrade King Spell"], ["Upgrade King Attack", "Upgrade King Attack", "Upgrade King Attack"], ["Upgrade King Attack", "Upgrade King Spell", "Upgrade King Spell"], ["Upgrade King Attack", "Upgrade King Attack", "Upgrade King Regen", "Upgrade King Regen", "Upgrade King Regen"], [], [], [], []], "opponentKingUpgradesPerWave": [[], [], [], [], [], [], [], [], [], [], [], [], [], [], [], []], "megamind": false, "chosenChampionLocation": "-1|-1"}]}